mapleapi/__init__.py
mapleapi/natayark.py
mapleapi/openfrp.py
mapleapi-1.1.0.dist-info/LICENSE
mapleapi-1.1.0.dist-info/METADATA
mapleapi-1.1.0.dist-info/WHEEL
mapleapi-1.1.0.dist-info/top_level.txt
mapleapi-1.1.0.dist-info/RECORD
